linux_aio/__init__.py
linux_aio/aio_context.py
linux_aio/aio_event.py
linux_aio/py.typed
linux_aio/block/__init__.py
linux_aio/block/base.py
linux_aio/block/non_rw.py
linux_aio/block/non_vector.py
linux_aio/block/rw.py
linux_aio/block/vector.py
linux_aio-0.4.1.dist-info/COPYING
linux_aio-0.4.1.dist-info/COPYING.LESSER
linux_aio-0.4.1.dist-info/METADATA
linux_aio-0.4.1.dist-info/WHEEL
linux_aio-0.4.1.dist-info/top_level.txt
linux_aio-0.4.1.dist-info/RECORD
